mavva/connectivity.py
mavva/logging.py
mavva/logic.py
mavva/snippet.py
mavva-0.2.0.dist-info/METADATA
mavva-0.2.0.dist-info/WHEEL
mavva-0.2.0.dist-info/top_level.txt
mavva-0.2.0.dist-info/RECORD
