Metadata-Version: 2.1
Name: mavva
Version: 0.2.0
Summary: An extendable MAVLink framework working straight out-of-the-box. I use it, maybe you will too
License: MIT
Classifier: Programming Language :: Python :: 3
Classifier: License :: OSI Approved :: MIT License
Classifier: Operating System :: OS Independent
Requires-Python: >=3.7
Requires-Dist: pymavlink ==2.4.37
Requires-Dist: pyserial ==3.5
